pdf_annotations_diff.py
pdf_annotations_diff-0.0.2.dist-info/LICENSE
pdf_annotations_diff-0.0.2.dist-info/METADATA
pdf_annotations_diff-0.0.2.dist-info/WHEEL
pdf_annotations_diff-0.0.2.dist-info/entry_points.txt
pdf_annotations_diff-0.0.2.dist-info/top_level.txt
pdf_annotations_diff-0.0.2.dist-info/RECORD
