Metadata-Version: 2.1
Name: pdf-annotations-diff
Version: 0.0.2
Summary: A tool to compare PDF annotations
Home-page: https://github.com/sam33r/pdf-annotations-diff
Author: Sameer Ahuja
Author-email: pdf-annotations-diff@sameerahuja.com
Classifier: Development Status :: 3 - Alpha
Classifier: Intended Audience :: Developers
Classifier: License :: OSI Approved :: MIT License
Classifier: Programming Language :: Python :: 3
Classifier: Programming Language :: Python :: 3.7
Classifier: Programming Language :: Python :: 3.8
Classifier: Programming Language :: Python :: 3.9
License-File: LICENSE
Requires-Dist: PyMuPDF
